Workbook

Sheet Допущения
A1: ЧекМудрец — Допущения модели
A3: 1. Стоимость API нейросети (OpenAI Vision / аналог)
A4: Стоимость обработки 1 чека (API-запрос), ₽ | B4: 3 | C4: ~$0.03 за запрос Vision API
A5: Кол-во бесплатных токенов/кредитов в месяц (₽) | B5: 1500 | C5: Стартовые кредиты / бесплатный tier
A7: 2. Хостинг и инфраструктура
A8: Сервер (VPS/облако), ₽/мес | B8: 800 | C8: Минимальный VPS ~800 ₽/мес
A9: Домен, ₽/год (делим на 12) | B9: 25 | C9: 300 ₽/год → 25 ₽/мес
A10: RuStore (публикация), ₽ | B10: 0 | C10: Публикация в RuStore бесплатна
A13: 3. Рост аудитории
A14: Пользователи — Мес 1 | B14: 30 | C14: Друзья, одногруппники, тестировщики
A15: Пользователи — Мес 2 | B15: 80 | C15: Сарафанное радио
A16: Пользователи — Мес 3 | B16: 200 | C16: RuStore + органический рост
A17: Пользователи — Мес 4 | B17: 400 | C17: Органический рост
A18: Пользователи — Мес 5 | B18: 700
A19: Пользователи — Мес 6 | B19: 1100
A20: Ср. чеков на пользователя в месяц | B20: 6 | C20: ~1-2 чека в неделю
A21: Доля платящих пользователей | B21: 0.05 | C21: 5% конверсия в платный тариф
A23: 4. Монетизация (Мес 4+)
A24: Цена подписки Premium, ₽/мес | B24: 199 | C24: Расширенная аналитика, советы, история
A25: Комиссия RuStore | B25: 0.05 | C25: 5% — комиссия RuStore
A27: 5. Разовые затраты на старте
A28: Инструменты разработки (IDE, тесты и пр.), ₽ | B28: 0 | C28: Бесплатно
A29: Дизайн (Figma — бесплатный тариф), ₽ | B29: 0 | C29: Бесплатно
A30: Публикация в RuStore (разово), ₽ | B30: 0 | C30: Бесплатно
A33: 6. Инструменты разработки — Claude Code
A34: Claude Pro (1 аккаунт на команду), $/мес | B34: 20 | C34: Один аккаунт на 5 человек
A35: Курс USD → RUB (для пересчёта) | B35: 90
A36: Claude Pro в рублях, ₽/мес | B36: =B34*B35 -> 1800

Sheet P&L по месяцам
A1: ЧекМудрец — P&L (Прибыли и убытки), ₽
A2: Статья | B2: Мес 1 (фев) | C2: Мес 2 (мар) | D2: Мес 3 (апр) | E2: Мес 4 (май) | F2: Мес 5 (июн) | G2: Мес 6 (июл) | H2: ИТОГО
A3: ПОЛЬЗОВАТЕЛИ
A4: Всего пользователей | B4: =Допущения!B14 -> 30 | C4: =Допущения!B15 -> 80 | D4: =Допущения!B16 -> 200 | E4: =Допущения!B17 -> 400 | F4: =Допущения!B18 -> 700 | G4: =Допущения!B19 -> 1100
A5: Кол-во чеков за месяц | B5: =B4*Допущения!B20 -> 180 | C5: =C4*Допущения!B20 -> 480 | D5: =D4*Допущения!B20 -> 1200 | E5: =E4*Допущения!B20 -> 2400 | F5: =F4*Допущения!B20 -> 4200 | G5: =G4*Допущения!B20 -> 6600 | H5: =SUM(B5:G5) -> 15060
A6: Платящих пользователей (Мес 4–6) | B6: - | C6: - | D6: - | E6: =ROUND(E4*Допущения!B21,0) -> 20 | F6: =ROUND(F4*Допущения!B21,0) -> 35 | G6: =ROUND(G4*Допущения!B21,0) -> 55 | H6: =SUM(B6:G6) -> 110
A8: ДОХОДЫ
A9: Выручка от подписок (до вычета комиссии) | B9: - | C9: - | D9: - | E9: =E6*Допущения!B24 -> 3980 | F9: =F6*Допущения!B24 -> 6965 | G9: =G6*Допущения!B24 -> 10945 | H9: =SUM(B9:G9) -> 21890
A10: Комиссия магазинов (−30%) | B10: - | C10: - | D10: - | E10: =-E9*Допущения!B25 -> -199 | F10: =-F9*Допущения!B25 -> -348.25 | G10: =-G9*Допущения!B25 -> -547.25 | H10: =SUM(B10:G10) -> -1094.5
A11: ИТОГО ВЫРУЧКА (чистая) | B11: =SUM(B9:B10) -> 0 | C11: =SUM(C9:C10) -> 0 | D11: =SUM(D9:D10) -> 0 | E11: =SUM(E9:E10) -> 3781 | F11: =SUM(F9:F10) -> 6616.75 | G11: =SUM(G9:G10) -> 10397.75 | H11: =SUM(H9:H10) -> 20795.5
A13: РАСХОДЫ
A14: API нейросети (Vision) | B14: =MAX(0,B5*Допущения!B4-Допущения!B5) -> 0 | C14: =MAX(0,C5*Допущения!B4-Допущения!B5) -> 0 | D14: =MAX(0,D5*Допущения!B4-Допущения!B5) -> 2100 | E14: =MAX(0,E5*Допущения!B4-Допущения!B5) -> 5700 | F14: =MAX(0,F5*Допущения!B4-Допущения!B5) -> 11100 | G14: =MAX(0,G5*Допущения!B4-Допущения!B5) -> 18300 | H14: =SUM(B14:G14) -> 37200
A15: Хостинг (VPS + домен) | B15: =Допущения!B8+Допущения!B9 -> 825 | C15: =Допущения!B8+Допущения!B9 -> 825 | D15: =Допущения!B8+Допущения!B9 -> 825 | E15: =Допущения!B8+Допущения!B9 -> 825 | F15: =Допущения!B8+Допущения!B9 -> 825 | G15: =Допущения!B8+Допущения!B9 -> 825 | H15: =SUM(B15:G15) -> 4950
A16: RuStore (публикация, разово) | B16: - | C16: - | D16: =Допущения!B31 -> 0 | E16: - | F16: - | G16: - | H16: =Допущения!B31 -> 0
A18: Claude Code (Pro подписка) | B18: =Допущения!B36 -> 1800 | C18: =Допущения!B36 -> 1800 | D18: =Допущения!B36 -> 1800 | E18: =Допущения!B36 -> 1800 | F18: =Допущения!B36 -> 1800 | G18: =Допущения!B36 -> 1800 | H18: =SUM(B18:G18) -> 10800
A19: ИТОГО РАСХОДЫ | B19: =SUM(B14:B18) -> 2625 | C19: =SUM(C14:C18) -> 2625 | D19: =SUM(D14:D18) -> 4725 | E19: =SUM(E14:E18) -> 8325 | F19: =SUM(F14:F18) -> 13725 | G19: =SUM(G14:G18) -> 20925 | H19: =SUM(H14:H18) -> 52950
A21: ИТОГ
A22: Прибыль / убыток за месяц | B22: =B11-B19 -> -2625 | C22: =C11-C19 -> -2625 | D22: =D11-D19 -> -4725 | E22: =E11-E19 -> -4544 | F22: =F11-F19 -> -7108.25 | G22: =G11-G19 -> -10527.25 | H22: =SUM(B22:G22) -> -32154.5
A23: Накопленный денежный поток (Cumulative) | B23: =B22 -> -2625 | C23: =B23+C22 -> -5250 | D23: =C23+D22 -> -9975 | E23: =D23+E22 -> -14519 | F23: =E23+F22 -> -21627.25 | G23: =F23+G22 -> -32154.5 | H23: =G23 -> -32154.5

Sheet Сводка
A1: ЧекМудрец — Сводка по проекту
A2: Показатель | B2: Значение | C2: Комментарий
A3: Горизонт расчёта | B3: 6 месяцев
A4: Зарплаты команды | B4: — (учебный проект) | C4: 5 человек, учебный проект
A6: ЗАТРАТЫ
A7: Разовые затраты (публикация в магазинах) | B7: ='P&L по месяцам'!D16+'P&L по месяцам'!D17 -> 0
A8: Регулярные затраты за 6 мес (хостинг + API) | B8: ='P&L по месяцам'!H14+'P&L по месяцам'!H15 -> 42150
A9: ИТОГО РАСХОДЫ за 6 мес | B9: ='P&L по месяцам'!H19 -> 52950 | C9: Основные: публикация приложений + сервер
A11: ДОХОДЫ
A12: Выручка чистая за 6 мес | B12: ='P&L по месяцам'!H11 -> 20795.5 | C12: После вычета 30% комиссии магазинов
A14: ИТОГ
A15: Прибыль / убыток за 6 мес | B15: ='P&L по месяцам'!H21 -> 0 | C15: Без учёта стоимости труда команды
A16: Накопленный денежный поток к Мес 6 | B16: ='P&L по месяцам'!G22 -> -10527.25 | C16: Выход в плюс — зависит от конверсии
A18: МЕТРИКИ
A19: Пользователей к концу Мес 6 | B19: =Допущения!B19 -> 1100
A20: Всего обработано чеков за 6 мес | B20: ='P&L по месяцам'!H5 -> 15060 | C20: North Star Metric
A21: Платящих пользователей в Мес 6 | B21: ='P&L по месяцам'!G6 -> 55
